defense_finder/__init__.py
defense_finder_cli/__init__.py
defense_finder_cli/_version.py
defense_finder_cli/main.py
defense_finder_posttreat/__init__.py
defense_finder_posttreat/best_solution.py
defense_finder_posttreat/df_genes.py
defense_finder_posttreat/df_hmmer.py
defense_finder_posttreat/df_systems.py
defense_finder_updater/__init__.py
mdmparis_defense_finder-2.0.1.dist-info/licenses/LICENSE
mdmparis_defense_finder-2.0.1.dist-info/METADATA
mdmparis_defense_finder-2.0.1.dist-info/WHEEL
mdmparis_defense_finder-2.0.1.dist-info/entry_points.txt
mdmparis_defense_finder-2.0.1.dist-info/top_level.txt
mdmparis_defense_finder-2.0.1.dist-info/RECORD
