Metadata-Version: 2.4
Name: mdmparis-defense-finder
Version: 2.0.1
Summary: Defense Finder: allow for a systematic search of all known anti-phage systems.
Home-page: https://github.com/mdmparis/defense-finder
Author: Jean Cury
Author-email: jean.cury@normalesup.org
License: GPLv3
Classifier: Development Status :: 4 - Beta
Classifier: Environment :: Console
Classifier: Operating System :: POSIX
Classifier: Programming Language :: Python :: 3
Classifier: Programming Language :: Python :: 3.10
Classifier: Programming Language :: Python :: 3.11
Classifier: Programming Language :: Python :: 3.12
Classifier: License :: OSI Approved :: GNU General Public License v3 (GPLv3)
Classifier: Intended Audience :: Science/Research
Classifier: Topic :: Scientific/Engineering :: Bio-Informatics
Requires-Python: >=3.10
License-File: LICENSE
Requires-Dist: macsyfinder==2.1.4
Requires-Dist: colorlog==6.3.0a1
Requires-Dist: click==8.0.3
Requires-Dist: pyhmmer
Requires-Dist: pyrodigal
Requires-Dist: pandas
Provides-Extra: dev
Requires-Dist: coverage; extra == "dev"
Dynamic: author
Dynamic: author-email
Dynamic: classifier
Dynamic: description
Dynamic: description-content-type
Dynamic: home-page
Dynamic: license
Dynamic: license-file
Dynamic: provides-extra
Dynamic: requires-dist
Dynamic: requires-python
Dynamic: summary
